{
  "packages": [
    {
      "name": "nanocodebug",
      "maintainer": "NanoCodeBug",
      "websiteUrl": "https://nanocodebug.com",
      "Url": "https://nanocodebug.github.io/",
      "email": "info@nanocodebug.com",
      "platforms": [
        {
          "name": "PawPet SAMD Boards",
          "architecture": "samd",
          "version": "1.0.3",
          "deprecated": false,
          "category": "NanoCodeBug",
          "url": "https://raw.githubusercontent.com/NanoCodeBug/pawpet/main/board/pawpet-1.0.3.zip",
          "archiveFileName": "pawpet-1.0.3.zip",
          "checksum": "SHA-256:061C10BEE6CAC85BA6FB0A2F53FAC917100C759A9CE35F11C0DA7A544DF53317",
          "size": 627443,
          "boards": [
            {
              "name": "PawPet M0"
            }
          ],
          "help": {
            "online": "https://forums.adafruit.com"
          },
          "toolsDependencies": [
            {
              "packager": "adafruit",
              "name": "arm-none-eabi-gcc",
              "version": "9-2019q4"
            },
            {
              "packager": "arduino",
              "name": "bossac",
              "version": "1.8.0-48-gb176eee"
            },
            {
              "packager": "arduino",
              "name": "openocd",
              "version": "0.10.0-arduino7"
            },
            {
              "packager": "adafruit",
              "name": "CMSIS",
              "version": "5.4.0"
            },
            {
              "packager": "adafruit",
              "name": "CMSIS-Atmel",
              "version": "1.2.2"
            }
          ],
          "discoveryDependencies": [],
          "monitorDependencies": []
        }
      ],
      "tools": [
      ],
      "help": {
        "online": "https://nanocodebug.com"
      }
    }
  ],
  "IsTrusted": false
}